temptorgbw_pkg/TemperatureToRGBW.py
temptorgbw_pkg/__init__.py
temp_to_rgbw-0.0.5.dist-info/LICENSE
temp_to_rgbw-0.0.5.dist-info/METADATA
temp_to_rgbw-0.0.5.dist-info/WHEEL
temp_to_rgbw-0.0.5.dist-info/top_level.txt
temp_to_rgbw-0.0.5.dist-info/RECORD
